elementary_math/__init__.py
elementary_math/__init__.pyc
elementary_math/operators.py
elementary_math/operators.pyc
elementary_math/zzz_ezinstall.py
elementary_math/add/__init__.py
elementary_math/add/__init__.pyc
elementary_math/data/data.json
elementary_math/div/__init__.py
elementary_math/div/__init__.pyc
elementary_math/mul/__init__.py
elementary_math/mul/__init__.pyc
elementary_math/pkg/__init__.py
elementary_math/pkg/module1.py
elementary_math/pkg/module2.py
elementary_math/sub/__init__.py
elementary_math/sub/__init__.pyc
elementary_math-0.0.8.dist-info/DESCRIPTION.rst
elementary_math-0.0.8.dist-info/METADATA
elementary_math-0.0.8.dist-info/RECORD
elementary_math-0.0.8.dist-info/WHEEL
elementary_math-0.0.8.dist-info/metadata.json
elementary_math-0.0.8.dist-info/top_level.txt
